setup.py
smapi/__init__.py
smapi/smapi.py
smartermail_api.egg-info/PKG-INFO
smartermail_api.egg-info/SOURCES.txt
smartermail_api.egg-info/dependency_links.txt
smartermail_api.egg-info/requires.txt
smartermail_api.egg-info/top_level.txt