Metadata-Version: 2.1
Name: smartermail-api
Version: 0.2.0
Summary: This is a simple python wrapper for the SmarterMail API.
Home-page: https://github.com/zjs81/SmarterToolsPythonWrapper
Author: Zachary Sylvester
Author-email: zacharysylvester81@gmail.com
